flask_batteries/.DS_Store
flask_batteries/__init__.py
flask_batteries/__pycache__/__init__.cpython-39.pyc
flask_batteries/__pycache__/destroy.cpython-39.pyc
flask_batteries/__pycache__/new.cpython-39.pyc
flask_batteries/commands/__init__.py
flask_batteries/commands/build.py
flask_batteries/commands/destroy.py
flask_batteries/commands/generate.py
flask_batteries/commands/install.py
flask_batteries/commands/new.py
flask_batteries/commands/uninstall.py
flask_batteries/commands/watch.py
flask_batteries/commands/__pycache__/__init__.cpython-39.pyc
flask_batteries/commands/__pycache__/build.cpython-39.pyc
flask_batteries/commands/__pycache__/destroy.cpython-39.pyc
flask_batteries/commands/__pycache__/generate.cpython-39.pyc
flask_batteries/commands/__pycache__/install.cpython-39.pyc
flask_batteries/commands/__pycache__/new.cpython-39.pyc
flask_batteries/commands/__pycache__/uninstall.cpython-39.pyc
flask_batteries/commands/__pycache__/watch.cpython-39.pyc
flask_batteries/installers/__init__.py
flask_batteries/installers/base_installer.py
flask_batteries/installers/flask_sqlalchemy.py
flask_batteries/installers/__pycache__/__init__.cpython-39.pyc
flask_batteries/installers/__pycache__/base_installer.cpython-39.pyc
flask_batteries/installers/__pycache__/flask_sqlalchemy.cpython-39.pyc
flask_batteries/template/.gitignore
flask_batteries/template/README.md
flask_batteries/template/main.py
flask_batteries/template/package.json
flask_batteries/template/webpack.config.js
flask_batteries/template/src/__init__.py
flask_batteries/template/src/config.py
flask_batteries/template/src/__pycache__/__init__.cpython-39.pyc
flask_batteries/template/src/assets/.DS_Store
flask_batteries/template/src/assets/images/flask-icon.png
flask_batteries/template/src/assets/images/flask-logo.png
flask_batteries/template/src/assets/javascript/index.js
flask_batteries/template/src/assets/stylesheets/base.scss
flask_batteries/template/src/assets/stylesheets/styles.scss
flask_batteries-0.0.0.dist-info/LICENSE
flask_batteries-0.0.0.dist-info/METADATA
flask_batteries-0.0.0.dist-info/WHEEL
flask_batteries-0.0.0.dist-info/entry_points.txt
flask_batteries-0.0.0.dist-info/top_level.txt
flask_batteries-0.0.0.dist-info/RECORD
