Metadata-Version: 2.1
Name: flask-batteries
Version: 0.0.0
Summary: A simple command line tool for bootstrapping flask applications.
Home-page: https://github.com/graydenshand/flask-batteries
Author: Grayden Shand
Author-email: graydenshand@gmail.com
License: UNKNOWN
Platform: UNKNOWN
Classifier: Programming Language :: Python :: 3
Classifier: License :: OSI Approved :: MIT License
Classifier: Operating System :: OS Independent
Requires-Python: >=3.6
License-File: LICENSE
Requires-Dist: requests
Requires-Dist: click
Requires-Dist: pathspec
Requires-Dist: jinja2
Requires-Dist: Flask
